LICENSE
naif_de440/__init__.py
naif_de440/de440.bsp
naif_de440/de440.md5
naif_de440/fetch.py
naif_de440/tests/__init__.py
naif_de440/tests/test_naif_de440.py
naif_de440-2020.12.21.1.dist-info/licenses/LICENSE
naif_de440-2020.12.21.1.dist-info/METADATA
naif_de440-2020.12.21.1.dist-info/WHEEL
naif_de440-2020.12.21.1.dist-info/top_level.txt
naif_de440-2020.12.21.1.dist-info/RECORD
