Metadata-Version: 2.4
Name: naif_de440
Version: 2020.12.21.1
Summary: NAIF Development Ephemeris (DE) 440 for SPICE
Author-email: B612 Asteroid Institute <info@b612foundation.org>
License: MIT License
Requires-Python: >=3.7
License-File: LICENSE
Provides-Extra: tests
Requires-Dist: pytest; extra == "tests"
Requires-Dist: spiceypy; extra == "tests"
Dynamic: license-file
